djelm/__init__.py
djelm/apps.py
djelm/cookiecutter.py
djelm/effect.py
djelm/elm.py
djelm/flag_loader.py
djelm/generators.py
djelm/npm.py
djelm/settings.py
djelm/strategy.py
djelm/subprocess.py
djelm/utils.py
djelm/validate.py
djelm/codegen/annotation.py
djelm/codegen/compiler.py
djelm/codegen/elm.py
djelm/codegen/expression.py
djelm/codegen/format.py
djelm/codegen/module_name.py
djelm/codegen/op.py
djelm/codegen/pattern.py
djelm/codegen/range.py
djelm/codegen/utils.py
djelm/codegen/writer.py
djelm/cookiecutters/entrypoint_template/cookiecutter.json
djelm/cookiecutters/entrypoint_template/{{cookiecutter.dir}}/{{cookiecutter.base_name}}{{cookiecutter.program_name}}.ts
djelm/cookiecutters/handlers_template/cookiecutter.json
djelm/cookiecutters/handlers_template/{{cookiecutter.dir}}/{{cookiecutter.program_name}}.handlers.ts
djelm/cookiecutters/program_flags_template/cookiecutter.json
djelm/cookiecutters/program_flags_template/{{cookiecutter.dir}}/{{cookiecutter.flag_file}}.py
djelm/cookiecutters/program_model_template/cookiecutter.json
djelm/cookiecutters/program_model_template/{{cookiecutter.dir}}/{{cookiecutter.program_name}}.elm
djelm/cookiecutters/program_tags_template/cookiecutter.json
djelm/cookiecutters/program_tags_template/{{cookiecutter.dir}}/{{cookiecutter.tag_name}}_tags.py
djelm/cookiecutters/program_template/cookiecutter.json
djelm/cookiecutters/program_template/{{cookiecutter.dir}}/{{cookiecutter.program_name}}.elm
djelm/cookiecutters/program_widget_ModelChoiceField_flags_template/cookiecutter.json
djelm/cookiecutters/program_widget_ModelChoiceField_flags_template/{{cookiecutter.dir}}/modelChoiceField.py
djelm/cookiecutters/program_widget_ModelChoiceField_tags_template/cookiecutter.json
djelm/cookiecutters/program_widget_ModelChoiceField_tags_template/{{cookiecutter.dir}}/modelChoiceField_widget_tags.py
djelm/cookiecutters/program_widget_ModelChoiceField_template/cookiecutter.json
djelm-0.22.5.dist-info/licenses/LICENSE.txt
djelm-0.22.5.dist-info/METADATA
djelm-0.22.5.dist-info/WHEEL
djelm-0.22.5.dist-info/top_level.txt
djelm-0.22.5.dist-info/RECORD
