Metadata-Version: 2.4
Name: djelm
Version: 0.22.5
Summary: A framework for using Elm programs in a Django project
Author-email: Confidenceman02 <john.terreu@gmail.com>
Project-URL: repository, https://github.com/Confidenceman02/django-elm
Project-URL: changelog, https://github.com/Confidenceman02/django-elm/blob/main/CHANGELOG.md
Project-URL: issues, https://github.com/Confidenceman02/django-elm/issues
Keywords: django,elm
Classifier: Development Status :: 4 - Beta
Classifier: Intended Audience :: Developers
Classifier: License :: OSI Approved :: MIT License
Classifier: Programming Language :: Python :: 3.11
Classifier: Operating System :: OS Independent
Classifier: Topic :: Software Development :: Libraries
Classifier: Topic :: Utilities
Classifier: Environment :: Web Environment
Classifier: Framework :: Django
Requires-Python: >=3.11
License-File: LICENSE.txt
Requires-Dist: django>=4.2.5
Requires-Dist: pydantic>=2.4.2
Requires-Dist: watchfiles>=0.21.0
Requires-Dist: aiofiles>=24.1.0
Requires-Dist: cookiecutter<3.0.0,>=2.6.0
Dynamic: license-file
